sensirion_sensorbridge_i2c_sfm/__init__.py
sensirion_sensorbridge_i2c_sfm/crc_calculator.py
sensirion_sensorbridge_i2c_sfm/sensirion_word_command.py
sensirion_sensorbridge_i2c_sfm/version.py
sensirion_sensorbridge_i2c_sfm/sfm3019/__init__.py
sensirion_sensorbridge_i2c_sfm/sfm3019/commands.py
sensirion_sensorbridge_i2c_sfm/sfm3019/device.py
sensirion_sensorbridge_i2c_sfm/sfm3019/sfm3019_constants.py
sensirion_sensorbridge_i2c_sfm-0.2.0.dist-info/LICENSE
sensirion_sensorbridge_i2c_sfm-0.2.0.dist-info/METADATA
sensirion_sensorbridge_i2c_sfm-0.2.0.dist-info/WHEEL
sensirion_sensorbridge_i2c_sfm-0.2.0.dist-info/top_level.txt
sensirion_sensorbridge_i2c_sfm-0.2.0.dist-info/RECORD
